fill_enum/__init__.py
fill_enum/fill_enum.py
fill_enum-0.1.0.dist-info/LICENSE
fill_enum-0.1.0.dist-info/WHEEL
fill_enum-0.1.0.dist-info/METADATA
fill_enum-0.1.0.dist-info/RECORD
