Metadata-Version: 2.1
Name: fill_enum
Version: 0.1.0
Summary: Decorator to automatically create Enum with filled values
Home-page: https://github.com/ivanovart/fill_enum
License: UNKNOWN
Author: Fabian Raab
Author-email: fabian@raab.link
Classifier: License :: OSI Approved :: MIT License
